{
    "files": [
        {
            "filename": "task_service.py",
            "code_content": "from typing import List, Optional\nfrom backend.models.task import Task, TaskCreate, TaskUpdate\n\n\nclass TaskService:\n    \"\"\"Service for Task entity business logic and CRUD operations.\"\"\"\n    \n    async def create_task(self, task_data: TaskCreate) -> Task:\n        \"\"\"Create a new task.\n        \n        Args:\n            task_data: Task creation data\n            \n        Returns:\n            Created task domain model\n        \"\"\"\n        # TODO: Implement database persistence\n        task = Task(\n            title=task_data.title,\n            description=task_data.description,\n        )\n        return task\n    \n    async def get_task_by_id(self, task_id: int) -> Optional[Task]:\n        \"\"\"Get a task by ID.\n        \n        Args:\n            task_id: Task identifier\n            \n        Returns:\n            Task domain model if found, None otherwise\n        \"\"\"\n        # TODO: Implement database query\n        return None\n    \n    async def list_tasks(self) -> List[Task]:\n        \"\"\"Get all tasks.\n        \n        Returns:\n            List of all task domain models\n        \"\"\"\n        # TODO: Implement database query\n        return []\n    \n    async def update_task(self, task_id: int, task_data: TaskUpdate) -> Optional[Task]:\n        \"\"\"Update an existing task.\n        \n        Args:\n            task_id: Task identifier\n            task_data: Task update data (partial)\n            \n        Returns:\n            Updated task domain model if found, None otherwise\n        \"\"\"\n        # TODO: Implement database update\n        return None\n    \n    async def delete_task(self, task_id: int) -> None:\n        \"\"\"Delete a task by ID.\n        \n        Args:\n            task_id: Task identifier\n        \"\"\"\n        # TODO: Implement database deletion\n        pass\n"
        }
    ],
    "warnings": [],
    "metadata": {
        "services_created": 1,
        "entities_covered": [
            "Task"
        ],
        "total_lines": 85,
        "functions_created": 5,
        "operations_implemented": {
            "Task": [
                "create",
                "read",
                "update",
                "delete"
            ]
        },
        "constraints_respected": null,
        "assumptions_made": null
    },
    "test_case_index": 0,
    "entities": {
        "Task": {
            "description": "A task item with a short title and an optional longer description used to track work to be done.",
            "fields": {
                "title": {
                    "type": "string",
                    "required": true
                },
                "description": {
                    "type": "string",
                    "required": false
                }
            },
            "id_strategy": "auto_increment",
            "natural_key_field": null
        }
    },
    "backend_services_spec": {
        "services": [
            {
                "entity": "Task",
                "functions": [
                    {
                        "name": "create_task",
                        "inputs": [
                            "TaskCreate"
                        ],
                        "returns": "Task",
                        "operation": "create"
                    },
                    {
                        "name": "get_task_by_id",
                        "inputs": [
                            "int"
                        ],
                        "returns": "Task",
                        "operation": "read"
                    },
                    {
                        "name": "list_tasks",
                        "inputs": [],
                        "returns": "List[Task]",
                        "operation": "read"
                    },
                    {
                        "name": "update_task",
                        "inputs": [
                            "int",
                            "TaskUpdate"
                        ],
                        "returns": "Task",
                        "operation": "update"
                    },
                    {
                        "name": "delete_task",
                        "inputs": [
                            "int"
                        ],
                        "returns": "None",
                        "operation": "delete"
                    }
                ]
            }
        ]
    }
}